pylegend/__init__.py
pylegend/_typing.py
pylegend/core/__init__.py
pylegend/core/database/__init__.py
pylegend/core/database/sql_to_string/__init__.py
pylegend/core/database/sql_to_string/config.py
pylegend/core/database/sql_to_string/db_extension.py
pylegend/core/database/sql_to_string/generator.py
pylegend/core/language/__init__.py
pylegend/core/language/legacy_api/__init__.py
pylegend/core/language/legacy_api/aggregate_specification.py
pylegend/core/language/legacy_api/legacy_api_tds_row.py
pylegend/core/language/legendql_api/__init__.py
pylegend/core/language/legendql_api/legendql_api_custom_expressions.py
pylegend/core/language/legendql_api/legendql_api_tds_row.py
pylegend/core/language/pandas_api/__init__.py
pylegend/core/language/pandas_api/pandas_api_aggregate_specification.py
pylegend/core/language/pandas_api/pandas_api_custom_expressions.py
pylegend/core/language/pandas_api/pandas_api_series.py
pylegend/core/language/pandas_api/pandas_api_tds_row.py
pylegend/core/language/shared/__init__.py
pylegend/core/language/shared/column_expressions.py
pylegend/core/language/shared/expression.py
pylegend/core/language/shared/functions.py
pylegend/core/language/shared/helpers.py
pylegend/core/language/shared/literal_expressions.py
pylegend/core/language/shared/operations/__init__.py
pylegend/core/language/shared/operations/binary_expression.py
pylegend/core/language/shared/operations/boolean_operation_expressions.py
pylegend/core/language/shared/operations/collection_operation_expressions.py
pylegend/core/language/shared/operations/date_operation_expressions.py
pylegend/core/language/shared/operations/float_operation_expressions.py
pylegend/core/language/shared/operations/integer_operation_expressions.py
pylegend/core/language/shared/operations/nary_expression.py
pylegend/core/language/shared/operations/nullary_expression.py
pylegend/core/language/shared/operations/number_operation_expressions.py
pylegend-0.12.0.dist-info/METADATA
pylegend-0.12.0.dist-info/WHEEL
pylegend-0.12.0.dist-info/licenses/LICENSE
pylegend-0.12.0.dist-info/licenses/LICENSE.spdx
pylegend-0.12.0.dist-info/licenses/NOTICE
pylegend-0.12.0.dist-info/RECORD
