Metadata-Version: 2.4
Name: pylegend
Version: 0.12.0
Summary: Python language binding for Legend data management platform
License: Apache-2.0
License-File: LICENSE
License-File: LICENSE.spdx
License-File: NOTICE
Author: PyLegend Maintainers
Author-email: legend@finos.org
Requires-Python: >=3.9,<3.14
Classifier: License :: OSI Approved :: Apache Software License
Classifier: Programming Language :: Python :: 3
Classifier: Programming Language :: Python :: 3.9
Classifier: Programming Language :: Python :: 3.10
Classifier: Programming Language :: Python :: 3.11
Classifier: Programming Language :: Python :: 3.12
Classifier: Programming Language :: Python :: 3.13
Requires-Dist: ijson (>=3.1.4)
Requires-Dist: numpy (>=1.20.0) ; python_version < "3.12"
Requires-Dist: numpy (>=1.26.0) ; python_version >= "3.12"
Requires-Dist: pandas (>=1.0.0) ; python_version < "3.12"
Requires-Dist: pandas (>=2.1.1) ; python_version >= "3.12"
Requires-Dist: requests (>=2.27.1)
Project-URL: Repository, https://github.com/finos/pylegend
